odoo10_addon_hr_employee_id-10.0.1.1.0-py2.7-nspkg.pth
odoo/addons/hr_employee_id/README.rst
odoo/addons/hr_employee_id/__init__.py
odoo/addons/hr_employee_id/__manifest__.py
odoo/addons/hr_employee_id/data/hr_employee_sequence.xml
odoo/addons/hr_employee_id/i18n/ar.po
odoo/addons/hr_employee_id/i18n/de.po
odoo/addons/hr_employee_id/i18n/es.po
odoo/addons/hr_employee_id/i18n/fi.po
odoo/addons/hr_employee_id/i18n/fr.po
odoo/addons/hr_employee_id/i18n/hr.po
odoo/addons/hr_employee_id/i18n/hr_HR.po
odoo/addons/hr_employee_id/i18n/it.po
odoo/addons/hr_employee_id/i18n/nl_NL.po
odoo/addons/hr_employee_id/i18n/pt_BR.po
odoo/addons/hr_employee_id/i18n/ro.po
odoo/addons/hr_employee_id/i18n/sl.po
odoo/addons/hr_employee_id/models/__init__.py
odoo/addons/hr_employee_id/models/hr_employee.py
odoo/addons/hr_employee_id/models/res_company.py
odoo/addons/hr_employee_id/models/res_config.py
odoo/addons/hr_employee_id/tests/__init__.py
odoo/addons/hr_employee_id/tests/test_employee_id.py
odoo/addons/hr_employee_id/views/hr_employee_views.xml
odoo/addons/hr_employee_id/views/res_config_views.xml
odoo10_addon_hr_employee_id-10.0.1.1.0.dist-info/DESCRIPTION.rst
odoo10_addon_hr_employee_id-10.0.1.1.0.dist-info/METADATA
odoo10_addon_hr_employee_id-10.0.1.1.0.dist-info/RECORD
odoo10_addon_hr_employee_id-10.0.1.1.0.dist-info/WHEEL
odoo10_addon_hr_employee_id-10.0.1.1.0.dist-info/metadata.json
odoo10_addon_hr_employee_id-10.0.1.1.0.dist-info/namespace_packages.txt
odoo10_addon_hr_employee_id-10.0.1.1.0.dist-info/top_level.txt
