Metadata-Version: 2.0
Name: odoo10-addon-hr-employee-id
Version: 10.0.1.1.0
Summary: Employee ID
Home-page: http://miketelahun.wordpress.com
Author: Michael Telahun Makonnen, OpenSynergy Indonesia,Camptocamp,Odoo Community Association (OCA)
Author-email: support@odoo-community.org
License: AGPL-3
Platform: UNKNOWN
Classifier: Programming Language :: Python
Classifier: Framework :: Odoo
Classifier: License :: OSI Approved :: GNU Affero General Public License v3
Requires-Python: ~=2.7
Requires-Dist: odoo (<10.1dev,>=10.0)
